kautolog/__init__.py
kautolog/cli.py
kautolog/installer.py
kautolog/templates/bashrc_autologger.sh
kautolog/templates/kautolog-replay
kautolog/templates/logrotate_terminal-logs
kautolog/templates/tmux_autologger.conf
kautolog/templates/zshrc_autologger.sh
kautolog/templates/systemd/autologger-rclone-sync.service
kautolog/templates/systemd/autologger-rclone-sync.timer
kautolog-1.1.14.dist-info/licenses/LICENSE.txt
kautolog-1.1.14.dist-info/METADATA
kautolog-1.1.14.dist-info/WHEEL
kautolog-1.1.14.dist-info/entry_points.txt
kautolog-1.1.14.dist-info/top_level.txt
kautolog-1.1.14.dist-info/RECORD
