Metadata-Version: 2.4
Name: kautolog
Version: 1.1.14
Summary: Kali/Linux auto-logging of all terminal sessions using script(1), with optional tmux, logrotate, and rclone sync.
Author-email: Mark Sowell <mark@marksowell.com>
License-Expression: MIT
Project-URL: Homepage, https://github.com/marksowell/kautolog
Project-URL: Issues, https://github.com/marksowell/kautolog/issues
Keywords: kali,linux,logging,terminal,script,tmux,logrotate,rclone
Requires-Python: >=3.8
License-File: LICENSE.txt
Requires-Dist: typer>=0.12.0
Dynamic: license-file
